feature_toggle_ui/__init__.py
feature_toggle_ui/feature_toggle_ui.py
widget_management_ui/__init__.py
widget_management_ui/widget_management_ui.py
alfa_integrations-0.0.1.dist-info/LICENSE
alfa_integrations-0.0.1.dist-info/METADATA
alfa_integrations-0.0.1.dist-info/WHEEL
alfa_integrations-0.0.1.dist-info/top_level.txt
alfa_integrations-0.0.1.dist-info/RECORD
